csweb/__init__.py
csweb/cli.py
csweb-0.1.0.dist-info/METADATA
csweb-0.1.0.dist-info/WHEEL
csweb-0.1.0.dist-info/entry_points.txt
csweb-0.1.0.dist-info/RECORD
