Metadata-Version: 2.4
Name: csweb
Version: 0.1.0
Summary: Compass Web - Web frontend and UI components for Compass Bot
Project-URL: Homepage, https://github.com/dagster-io/dagster-compass
Project-URL: Repository, https://github.com/dagster-io/dagster-compass
Project-URL: Issues, https://github.com/dagster-io/dagster-compass/issues
Author-email: Dagster Labs <hello@dagsterlabs.com>
License: Apache-2.0
Classifier: Development Status :: 3 - Alpha
Classifier: Intended Audience :: Developers
Classifier: License :: OSI Approved :: Apache Software License
Classifier: Programming Language :: Python :: 3
Classifier: Programming Language :: Python :: 3.13
Requires-Python: >=3.13
